py2lispIDyOM/__init__.py
py2lispIDyOM/configuration.py
py2lispIDyOM/export.py
py2lispIDyOM/extract.py
py2lispIDyOM/run.py
py2lispIDyOM/viz.py
py2lispIDyOM-1.0.2.dist-info/LICENSE
py2lispIDyOM-1.0.2.dist-info/METADATA
py2lispIDyOM-1.0.2.dist-info/WHEEL
py2lispIDyOM-1.0.2.dist-info/top_level.txt
py2lispIDyOM-1.0.2.dist-info/RECORD
