Metadata-Version: 2.1
Name: py2lispIDyOM
Version: 1.0.2
Summary: A Python package for the information dynamics of music (IDyOM) model
Home-page: https://github.com/xinyiguan/py2lispIDyOM
Author: Xinyi Guan
Author-email: xinyi.guan@nyu.edu
Classifier: Programming Language :: Python :: 3
Classifier: License :: OSI Approved :: MIT License
Classifier: Operating System :: OS Independent
Requires-Python: >=3.9
License-File: LICENSE
Requires-Dist: matplotlib (>=3.5.2)
Requires-Dist: numpy (>=1.22.3)
Requires-Dist: pandas (>=1.4.2)
Requires-Dist: scipy (>=1.8.0)
Requires-Dist: natsort (>=8.1.0)
